bytewax/_bytewax.cpython-311-x86_64-linux-gnu.so
bytewax/_bytewax.pyi
bytewax/_metrics.py
bytewax/_utils.py
bytewax/connectors/__init__.py
bytewax/connectors/demo.py
bytewax/connectors/files.py
bytewax/connectors/kafka/__init__.py
bytewax/connectors/kafka/operators.py
bytewax/connectors/kafka/serde.py
bytewax/connectors/stdio.py
bytewax/dataflow.py
bytewax/errors.py
bytewax/inputs.py
bytewax/operators/__init__.py
bytewax/operators/helpers.py
bytewax/operators/windowing.py
bytewax/outputs.py
bytewax/py.typed
bytewax/recovery.py
bytewax/run.py
bytewax/testing.py
bytewax/tracing.py
bytewax/visualize.py
bytewax_fork-0.22.0rc7.dist-info/METADATA
bytewax_fork-0.22.0rc7.dist-info/WHEEL
bytewax_fork-0.22.0rc7.dist-info/licenses/LICENSE
bytewax_fork-0.22.0rc7.dist-info/RECORD
