Metadata-Version: 2.4
Name: bytewax-fork
Version: 0.22.0rc7
Classifier: Development Status :: 4 - Beta
Classifier: Intended Audience :: Developers
Classifier: Operating System :: OS Independent
Classifier: Programming Language :: Rust
Classifier: Programming Language :: Python :: Implementation :: CPython
Classifier: Programming Language :: Python :: Implementation :: PyPy
Classifier: Programming Language :: Python :: 3
Classifier: Programming Language :: Python :: 3.10
Classifier: Programming Language :: Python :: 3.11
Classifier: Programming Language :: Python :: 3.12
Classifier: Topic :: System :: Networking
Classifier: Topic :: System :: Distributed Computing
Requires-Dist: typing-extensions>=4
Requires-Dist: prometheus-client>=0.18
Requires-Dist: requests>=2.0 ; extra == 'kafka'
Requires-Dist: fastavro>=1.8 ; extra == 'kafka'
Requires-Dist: confluent-kafka>=2.0.2 ; extra == 'kafka'
Provides-Extra: kafka
License-File: LICENSE
Requires-Python: >=3.10
Project-URL: Source Code, https://github.com/nrdhm/bytewax
Project-URL: Issues, https://github.com/nrdhm/bytewax/issues
Project-URL: Documentation, https://docs.bytewax.io/
Project-URL: Changelog, https://github.com/nrdhm/bytewax/blob/main/CHANGELOG.md
